{
    "nodes": [
        {
            "name": "Fullstack",
            "id": 0,
            "neighbors": [
                {
                    "id": 1,
                    "weight": 7
                },
                {
                    "id": 2,
                    "weight": 2
                },
                {
                    "id": 3,
                    "weight": 6
                }
            ]
        },
        {
            "name": "Dig Inn",
            "id": 1,
            "neighbors": [
                {
                    "id": 0,
                    "weight": 7
                },
                {
                    "id": 2,
                    "weight": 4
                },
                {
                    "id": 5,
                    "weight": 9
                }
            ]
        },
        {
            "name": "Dubliner",
            "id": 2,
            "neighbors": [
                {
                    "id": 0,
                    "weight": 2
                },
                {
                    "id": 1,
                    "weight": 4
                },
                {
                    "id": 3,
                    "weight": 3
                },
                {
                    "id": 4,
                    "weight": 7
                }
            ]
        },
        {
            "name": "Starbucks",
            "id": 3,
            "neighbors": [
                {
                    "id": 0,
                    "weight": 6
                },
                {
                    "id": 2,
                    "weight": 3
                },
                {
                    "id": 4,
                    "weight": 6
                }
            ]
        },
        {
            "name": "Cafe Grumpy",
            "id": 5,
            "neighbors": [
                {
                    "id": 1,
                    "weight": 9
                },
                {
                    "id": 4,
                    "weight": 5
                }
            ]
        },
        {
            "name": "Insomnia Cookies",
            "id": 4,
            "neighbors": [
                {
                    "id": 5,
                    "weight": 5
                },
                {
                    "id": 2,
                    "weight": 7
                },
                {
                    "id": 3,
                    "weight": 6
                }
            ]
        }
    ]
}   